promptstrike/__init__.py
promptstrike/ai-chunks/.claude/settings.local_ck0.md
promptstrike/ai-chunks/chromadb_install_log_ck0.md
promptstrike/ai-chunks/cli_ck0.md
promptstrike/ai-chunks/core/attacks_ck0.md
promptstrike/ai-chunks/core/report_ck0.md
promptstrike/ai-chunks/core/scanner_ck0.md
promptstrike/ai-chunks/models/scan_result_ck0.md
promptstrike/ai-chunks/utils/config_ck0.md
promptstrike/ai-chunks/utils/split-for-ai_ck0.md
promptstrike/chromadb_install_log.txt
promptstrike/cli.py
promptstrike/core/__init__.py
promptstrike/core/attacks.py
promptstrike/core/report.py
promptstrike/core/scanner.py
promptstrike/models/__init__.py
promptstrike/models/scan_result.py
promptstrike/promptstrike.yaml
promptstrike/utils/__init__.py
promptstrike/utils/config.py
promptstrike/utils/split-for-ai.py
promptstrike/utils/split-for-ai.py.bak
promptstrike-0.1.0.dist-info/METADATA
promptstrike-0.1.0.dist-info/WHEEL
promptstrike-0.1.0.dist-info/entry_points.txt
promptstrike-0.1.0.dist-info/RECORD
