Metadata-Version: 2.3
Name: promptstrike
Version: 0.1.0
Summary: Developer-first automated LLM red-team platform
License: MIT
Keywords: llm,security,red-team,owasp,ai-safety
Author: PromptStrike Team
Author-email: dev@promptstrike.com
Requires-Python: >=3.11,<4.0
Classifier: Development Status :: 3 - Alpha
Classifier: Intended Audience :: Developers
Classifier: License :: OSI Approved :: MIT License
Classifier: Programming Language :: Python :: 3
Classifier: Programming Language :: Python :: 3.11
Classifier: Programming Language :: Python :: 3.12
Classifier: Programming Language :: Python :: 3.13
Classifier: Topic :: Security
Classifier: Topic :: Software Development :: Testing
Requires-Dist: chromadb (>=0.4.18,<0.5.0)
Requires-Dist: click (>=8.1.7,<9.0.0)
Requires-Dist: httpx (>=0.26.0,<0.27.0)
Requires-Dist: jinja2 (>=3.1.2,<4.0.0)
Requires-Dist: openai (>=1.6.0,<2.0.0)
Requires-Dist: pydantic (>=2.5.0,<3.0.0)
Requires-Dist: python-dotenv (>=1.0.0,<2.0.0)
Requires-Dist: pyyaml (>=6.0.1,<7.0.0)
Requires-Dist: rich (>=13.7.0,<14.0.0)
Requires-Dist: tenacity (>=8.2.3,<9.0.0)
Requires-Dist: tqdm (>=4.66.0,<5.0.0)
Requires-Dist: typer (>=0.9.0,<0.10.0)
Project-URL: Documentation, https://docs.promptstrike.com
Project-URL: Homepage, https://github.com/siwenwang0803/PromptStrike
Project-URL: Repository, https://github.com/siwenwang0803/PromptStrike
